scdesigner/__init__.py
scdesigner/base/__init__.py
scdesigner/base/copula.py
scdesigner/base/marginal.py
scdesigner/base/simulator.py
scdesigner/copulas/__init__.py
scdesigner/copulas/standard_copula.py
scdesigner/data/__init__.py
scdesigner/data/formula.py
scdesigner/data/loader.py
scdesigner/datasets/__init__.py
scdesigner/datasets/pancreas.py
scdesigner/distributions/__init__.py
scdesigner/distributions/bernoulli.py
scdesigner/distributions/gaussian.py
scdesigner/distributions/negbin.py
scdesigner/distributions/negbin_irls.py
scdesigner/distributions/negbin_irls_funs.py
scdesigner/distributions/poisson.py
scdesigner/distributions/zero_inflated_negbin.py
scdesigner/distributions/zero_inflated_poisson.py
scdesigner/simulators/__init__.py
scdesigner/simulators/composite.py
scdesigner/simulators/positive_nonnegative_matrix_factorization.py
scdesigner/simulators/scd3.py
scdesigner/transform/__init__.py
scdesigner/transform/transform.py
scdesigner/utils/kwargs.py
scdesigner-0.0.13.dist-info/METADATA
scdesigner-0.0.13.dist-info/WHEEL
scdesigner-0.0.13.dist-info/RECORD
