Metadata-Version: 2.4
Name: scdesigner
Version: 0.0.13
Summary: Interactive simulation for rigorous and transparent multi-omics analysis.
Project-URL: Homepage, https://github.com/krisrs1128/scDesigner/
Project-URL: Issues, https://github.com/krisrs1128/scDesigner/Issues/
Author-email: Kris Sankaran <ksankaran@wisc.edu>
Classifier: License :: OSI Approved :: MIT License
Classifier: Operating System :: OS Independent
Classifier: Programming Language :: Python :: 3
Requires-Python: >=3.8
Requires-Dist: anndata
Requires-Dist: formulaic
Requires-Dist: numpy
Requires-Dist: pandas
Requires-Dist: rich
Requires-Dist: scanpy
Requires-Dist: scipy
Requires-Dist: torch
Requires-Dist: tqdm
